cggr.py
cggr_async.py
cggr_checkpointing.py
cggr_dataloader.py
cggr_flash.py
triton_kernels.py
cggr-0.5.0.dist-info/licenses/LICENSE
cggr-0.5.0.dist-info/METADATA
cggr-0.5.0.dist-info/WHEEL
cggr-0.5.0.dist-info/top_level.txt
cggr-0.5.0.dist-info/RECORD
