Metadata-Version: 2.4
Name: cggr
Version: 0.5.0
Summary: Confidence-Gated Gradient Routing for Efficient Transformer Training
Home-page: https://github.com/MinimaML/CGGR
Author: MinimaML
Classifier: Development Status :: 4 - Beta
Classifier: Intended Audience :: Science/Research
Classifier: License :: OSI Approved :: MIT License
Classifier: Programming Language :: Python :: 3
Classifier: Programming Language :: Python :: 3.8
Classifier: Programming Language :: Python :: 3.9
Classifier: Programming Language :: Python :: 3.10
Classifier: Programming Language :: Python :: 3.11
Classifier: Programming Language :: Python :: 3.12
Classifier: Topic :: Scientific/Engineering :: Artificial Intelligence
Classifier: Operating System :: OS Independent
Requires-Python: >=3.8
License-File: LICENSE
Requires-Dist: torch>=2.0.0
Provides-Extra: cuda
Requires-Dist: triton>=2.0.0; extra == "cuda"
Provides-Extra: flash
Requires-Dist: flash-attn>=2.0.0; extra == "flash"
Provides-Extra: dev
Requires-Dist: pytest; extra == "dev"
Requires-Dist: rich; extra == "dev"
Provides-Extra: benchmark
Requires-Dist: transformers; extra == "benchmark"
Requires-Dist: rich; extra == "benchmark"
Provides-Extra: all
Requires-Dist: triton>=2.0.0; extra == "all"
Requires-Dist: flash-attn>=2.0.0; extra == "all"
Requires-Dist: transformers; extra == "all"
Requires-Dist: rich; extra == "all"
Requires-Dist: pytest; extra == "all"
Dynamic: author
Dynamic: classifier
Dynamic: description
Dynamic: description-content-type
Dynamic: home-page
Dynamic: license-file
Dynamic: provides-extra
Dynamic: requires-dist
Dynamic: requires-python
Dynamic: summary
